setup.cfg
setup.py
pyepw/__init__.py
pyepw/calc.py
pyepw/epw.py
pyepw.egg-info/PKG-INFO
pyepw.egg-info/SOURCES.txt
pyepw.egg-info/dependency_links.txt
pyepw.egg-info/top_level.txt