Metadata-Version: 1.1
Name: pyepw
Version: 0.1
Summary: Python EPW file generator
Home-page: https://github.com/rbuffat/pyepw
Author: Rene Buffat
Author-email: buffat@gmail.com
License: Apache License 2.0
Download-URL: https://github.com/rbuffat/pyepw/tarball/0.1
Keywords: EnergyPlus,EPW
Platform: UNKNOWN
Classifier: Development Status :: 2 - Pre-Alpha
